cal_server.py
joe2025_uv_project-0.3.0.dist-info/METADATA
joe2025_uv_project-0.3.0.dist-info/WHEEL
joe2025_uv_project-0.3.0.dist-info/RECORD
