Metadata-Version: 2.4
Name: joe2025-uv-project
Version: 0.3.0
Summary: A calculator server with LangChain integration
Author-email: joe2025 <812030090@qq.com>
License: MIT
Classifier: Programming Language :: Python :: 3
Classifier: Programming Language :: Python :: 3.12
Requires-Python: >=3.12
Requires-Dist: langchain-openai==0.3.30
Provides-Extra: dev
Requires-Dist: pytest>=8; extra == 'dev'
